{
  "ホーム": "首頁",
  "パーティ": "隊伍",
  "娼館": "娼館",
  "ショップ": "商店",
  "ガチャ": "轉蛋",
  "クエスト": "任務",
  "探索隊": "探索隊",
  "イベント": "活動",
  "プレゼント": "禮物",
  "ミッション": "任務",
  "お知らせ": "公告",
  "施設": "設施",
  "開発計画": "開發計劃",
  "名前": "名字",
  "初心者\nミッション": "新手任務",
  "初心者ミッション": "新手任務",
  "入手": "獲得時間",
  "レアリティ": "稀有度",
  "ミッションパス": "任務通行證",
  "ミッション\nパス": "任務\n通行證",
  "おしごと用<br>コスチューム": "工作用<br>服裝",
  "通常用<br>コスチューム": "平時用<br>服裝",
  "コスチューム": "服裝",
  "キャラ詳細": "角色詳情",
  "ボーナス": "獎勵",
  "順調、順調♪<br>もっと可愛い女の子を紹介して頂戴♪": "不錯不錯♪ <br>再多介紹些可愛的女孩子給我嘛♪"
}
